algebraCalc/__init__.py
algebraCalc/formula.py
algebraCalc/matrix.py
algebraCalc/util.py
algebraCalc/vector.py
algebraCalc-1.0.5.dist-info/LICENCE
algebraCalc-1.0.5.dist-info/METADATA
algebraCalc-1.0.5.dist-info/WHEEL
algebraCalc-1.0.5.dist-info/top_level.txt
algebraCalc-1.0.5.dist-info/RECORD
